sagemaker_studio/__init__.py
sagemaker_studio/data_models.py
sagemaker_studio/domain.py
sagemaker_studio/project.py
sagemaker_studio/py.typed
sagemaker_studio/sagemaker_studio_api.py
sagemaker_studio/_openapi/__init__.py
sagemaker_studio/_openapi/exceptions.py
sagemaker_studio/_openapi/model_utils.py
sagemaker_studio/_openapi/model/__init__.py
sagemaker_studio/_openapi/model/compute.py
sagemaker_studio/_openapi/model/filter_by_tags.py
sagemaker_studio/_openapi/model/get_clone_url_request.py
sagemaker_studio/_openapi/model/get_clone_url_request_content.py
sagemaker_studio/_openapi/model/get_domain_execution_role_credentials_request.py
sagemaker_studio/_openapi/model/get_domain_execution_role_credentials_request_content.py
sagemaker_studio/_openapi/model/get_execution_request.py
sagemaker_studio/_openapi/model/get_execution_request_content.py
sagemaker_studio/_openapi/model/image_details.py
sagemaker_studio/_openapi/model/input_config.py
sagemaker_studio/_openapi/model/list_executions_request.py
sagemaker_studio/_openapi/model/list_executions_request_content.py
sagemaker_studio/_openapi/model/notebook_config.py
sagemaker_studio/_openapi/model/output_config.py
sagemaker_studio/_openapi/model/start_execution_request.py
sagemaker_studio/_openapi/model/start_execution_request_content.py
sagemaker_studio/_openapi/model/start_execution_request_notebook_config.py
sagemaker_studio/_openapi/model/start_execution_request_tags.py
sagemaker_studio/_openapi/model/stop_execution_request.py
sagemaker_studio/_openapi/model/stop_execution_request_content.py
sagemaker_studio/_openapi/model/termination_condition.py
sagemaker_studio/_openapi/models/__init__.py
sagemaker_studio/_test/__init__.py
sagemaker_studio/_test/test_sagemaker_studio_api.py
sagemaker_studio/_test/schema/__init__.py
sagemaker_studio/_test/schema/credentials/__init__.py
sagemaker_studio/_test/schema/credentials/test_credentials_schema.py
sagemaker_studio/_test/schema/execution/__init__.py
sagemaker_studio-1.1.3.dist-info/licenses/LICENSE
sagemaker_studio-1.1.3.dist-info/licenses/NOTICE
sagemaker_studio-1.1.3.dist-info/METADATA
sagemaker_studio-1.1.3.dist-info/WHEEL
sagemaker_studio-1.1.3.dist-info/top_level.txt
sagemaker_studio-1.1.3.dist-info/zip-safe
sagemaker_studio-1.1.3.dist-info/RECORD
