Metadata-Version: 2.4
Name: sagemaker_studio
Version: 1.1.3
Summary: Python library to interact with Amazon SageMaker Unified Studio
Home-page: https://aws.amazon.com/sagemaker/
Author: Amazon Web Services
License: Apache License 2.0
Keywords: AWS,Amazon,SageMaker,SageMaker Unified Studio,SDK
Platform: Linux
Platform: Mac OS X
Platform: Windows
Classifier: Programming Language :: Python
Classifier: Programming Language :: Python :: 3
Classifier: Programming Language :: Python :: 3.10
Classifier: Programming Language :: Python :: 3.11
Classifier: Programming Language :: Python :: 3.12
Classifier: License :: OSI Approved :: Apache Software License
Requires-Python: >=3.10
License-File: LICENSE
License-File: NOTICE
Requires-Dist: boto3>=1.34.106
Requires-Dist: botocore>=1.34.106
Requires-Dist: urllib3>=1.26.19
Requires-Dist: requests>=2.25.1
Requires-Dist: psutil>=5.9.8
Requires-Dist: python_dateutil>=2.5.3
Requires-Dist: setuptools>=21.0.0
Requires-Dist: packaging>=24.0
Requires-Dist: pyathena>=3.18.0
Requires-Dist: sqlalchemy>=2.0.43
Requires-Dist: pandas>=2.3.2
Requires-Dist: duckdb>=1.4.0
Requires-Dist: pymysql>=1.1.2
Requires-Dist: snowflake-sqlalchemy>=1.7.7
Requires-Dist: sqlalchemy-bigquery>=0.0.7
Requires-Dist: pydynamodb>=0.7.4
Requires-Dist: psycopg2-binary>=2.9.10
Requires-Dist: pymssql>=2.3.8
Requires-Dist: awswrangler>=3.5.0
Requires-Dist: pyiceberg>=0.7.0
Requires-Dist: numpy<2.3.0,>=1.26.4
Requires-Dist: pyarrow>=19.0.0
Requires-Dist: aws-embedded-metrics>=3.2.0
Provides-Extra: test
Requires-Dist: pytest>=6; extra == "test"
Requires-Dist: pytest-cov; extra == "test"
Requires-Dist: toml; extra == "test"
Requires-Dist: coverage; extra == "test"
Provides-Extra: dev
Requires-Dist: wheel; extra == "dev"
Requires-Dist: invoke; extra == "dev"
Requires-Dist: twine; extra == "dev"
Dynamic: author
Dynamic: classifier
Dynamic: description
Dynamic: description-content-type
Dynamic: home-page
Dynamic: keywords
Dynamic: license
Dynamic: license-file
Dynamic: platform
Dynamic: provides-extra
Dynamic: requires-dist
Dynamic: requires-python
Dynamic: summary
